larch_pickle-1.4.7.dist-info/RECORD
larch_pickle-1.4.7.dist-info/WHEEL
larch_pickle-1.4.7.dist-info/top_level.txt
larch_pickle-1.4.7.dist-info/METADATA
larch_pickle-1.4.7.dist-info/licenses/LICENSE
larch/pickle/pickle.cpython-312-darwin.so
larch/pickle/register.py
larch/pickle/__init__.py
