Metadata-Version: 2.1
Name: larch-pickle
Version: 1.4.7
Summary: A faster python pickle replacement
Home-page: https://github.com/kochelmonster/larch-pickle
Author: Michael Reithinger
Author-email: Michael Reithinger <mreithinger@web.de>
License: BSD-3-Clause
Keywords: library
Classifier: Development Status :: 5 - Production/Stable
Classifier: Intended Audience :: Developers
Classifier: Programming Language :: Python :: 3
Classifier: Topic :: Software Development :: Libraries :: Python Modules
License-File: LICENSE
Provides-Extra: build
Requires-Dist: cython; extra == "build"
Provides-Extra: documentation
Requires-Dist: sphinxcontrib-napoleon; extra == "documentation"
Requires-Dist: sphinxcontrib-plantuml; extra == "documentation"
